{
  "date_range": "1985-01-02 to 2025-11-25",
  "total_days": 10229,
  "mean_probability": 0.6424042083753373,
  "std_probability": 0.09859829395669498,
  "median_probability": 0.6925411782276899,
  "min_probability": 0.30028501044071265,
  "max_probability": 0.6950886664434418,
  "high_probability_days": 6600,
  "high_probability_pct": 64.5224362107733,
  "threshold": 0.5,
  "high_probability_periods": [
    {
      "start": "1987-04-10",
      "end": "1987-07-09"
    },
    {
      "start": "1989-07-24",
      "end": "1989-11-29"
    },
    {
      "start": "1990-07-06",
      "end": "1990-08-16"
    },
    {
      "start": "1991-08-02",
      "end": "1991-11-06"
    },
    {
      "start": "1992-02-12",
      "end": "1992-05-04"
    },
    {
      "start": "1992-06-02",
      "end": "1992-09-23"
    },
    {
      "start": "1992-10-14",
      "end": "1993-03-17"
    },
    {
      "start": "2001-06-21",
      "end": "2025-11-25"
    }
  ]
}